quackseq_simulator/__init__.py
quackseq_simulator/simulator.py
quackseq_simulator/simulator_controller.py
quackseq_simulator/simulator_model.py
quackseq_simulator-0.0.2.dist-info/METADATA
quackseq_simulator-0.0.2.dist-info/WHEEL
quackseq_simulator-0.0.2.dist-info/licenses/LICENSE
quackseq_simulator-0.0.2.dist-info/RECORD
